[
  {
    "departement": "44",
    "website": "",
    "_type": "dict",
    "description": "",
    "hour": "de 08h00 à 10h30",
    "city": "SAVENAY",
    "price": "6 €",
    "organisateur": "CYCLO VTT SAVENAY",
    "canceled": "true",
    "contact": "Voir site Veloenfrance.fr ou celui de l'organisateur",
    "date": "24/01/2021",
    "name": "SILLON-LAC"
  },
  {
    "departement": "35",
    "website": "",
    "_type": "dict",
    "description": "",
    "hour": "10h00 à 16h00",
    "city": "ARGENTRE DU PLESSIS",
    "price": "Bulletin d’inscription informatique :18€ par concurrent licencié ou non\r\n Bulletin d’inscription manuscrit    : 20€ par concurrent licencié ou non",
    "organisateur": "UCA - Groupe Vététistes",
    "canceled": "false",
    "contact": "6hvttargentre@gmail.com",
    "date": "23/05/2021",
    "name": "6 H VTT AU MOULIN NEUF"
  },
  {
    "departement": "56",
    "website": "",
    "_type": "dict",
    "description": "",
    "hour": "7h30 à 10h00",
    "city": "ALLAIRE",
    "price": "VTT :5€\r\nMarche: 4€\r\nCyclo : 3€",
    "organisateur": "Club Cyclo VTT Marche St Gaudence",
    "canceled": "false",
    "contact": "potier.remy@wanadoo.fr / 06 73 92 34 77",
    "date": "16/05/2021",
    "name": "25ème Ronde des Moulins"
  },
  {
    "departement": "29",
    "website": "",
    "_type": "dict",
    "description": "",
    "hour": "DE 7H30 à10H00",
    "city": "TREMEVEN",
    "price": "5 € VTT / 4 € Marche",
    "organisateur": "VELO SPORT TREMEVENOIS",
    "canceled": "false",
    "contact": "Tél: 06 76 73 22 61   florian.perron@hotmail.fr ou 0616404024  thierry.cochevelou@orange.FR",
    "date": "16/05/2021",
    "name": "RANDO DES DEUX RIVIERES"
  },
  {
    "departement": "29",
    "website": "",
    "_type": "dict",
    "description": "",
    "hour": "à partir de 15 heures le  15 mai 2021",
    "city": "GUILERS",
    "price": "42 € adulte - 21 € jeunes, repas du soir et petit déjeuner compris, camping gratuit",
    "organisateur": "GUILERS VTT NATURE",
    "canceled": "false",
    "contact": "jean-jacques.cadalen@wanadoo.fr",
    "date": "15/05/2021",
    "name": "24 HEURES DU PAYS DE BREST - 20 EME EDITION"
  },
  {
    "departement": "56",
    "website": "",
    "_type": "dict",
    "description": "",
    "hour": "7 H 30",
    "city": "PEAULE",
    "price": "",
    "organisateur": "APNP et Armoricaine Cyclo-VTT",
    "canceled": "false",
    "contact": "jpch0955@gmail.com",
    "date": "9/05/2021",
    "name": "Rando ds Poulpikans"
  },
  {
    "departement": "35",
    "website": "",
    "_type": "dict",
    "description": "",
    "hour": "Départ de 7H30 à 10H30 - Fermeture des parcours 13H",
    "city": "DOL-DE-BRETAGNE",
    "price": "5€ pour le VTT\r\n3€ pour le pédestre\r\nGratuit pour les enfants de -12 ans",
    "organisateur": "APEL ECOLE NOTRE-DAME",
    "canceled": "false",
    "contact": "randoladoloise@gmail.com",
    "date": "9/05/2021",
    "name": "LA DOLOISE"
  },
  {
    "departement": "22",
    "website": "",
    "_type": "dict",
    "description": "",
    "hour": "7h30",
    "city": "CREHEN",
    "price": "5€ route et vtt 4€pedestre",
    "organisateur": "émeraude cyclo vtt Crehen",
    "canceled": "false",
    "contact": "fabdaligot@free.fr",
    "date": "9/05/2021",
    "name": "17 éime virade de l'émeraude"
  },
  {
    "departement": "35",
    "website": "",
    "_type": "dict",
    "description": "",
    "hour": "Départ de 14H00 à 16H30 - Fermeture des parcours 19H",
    "city": "DOL-DE-BRETAGNE",
    "price": "5€ pour le VTT\r\n3€ pour le pédestre\r\nGratuit pour les enfants de -12ans",
    "organisateur": "APEL ECOLE NOTRE-DAME",
    "canceled": "false",
    "contact": "randoladoloise@gmail.com",
    "date": "08/05/2021",
    "name": "LA DOLOISE"
  },
  {
    "departement": "22",
    "website": "",
    "_type": "dict",
    "description": "",
    "hour": "13h30",
    "city": "CREHEN",
    "price": "5€ route et vtt 7e raid vtt(80km)",
    "organisateur": "émeraude cyclo vtt Crehen",
    "canceled": "false",
    "contact": "fabdaligot@free.fr",
    "date": "08/05/2021",
    "name": "17éime virade de l'émeraude"
  },
  {
    "departement": "35",
    "website": "",
    "_type": "dict",
    "description": "",
    "hour": "7h30 le dimanche",
    "city": "SAINT MALON SUR MEL",
    "price": "",
    "organisateur": "Brocéliande sport Malonnais",
    "canceled": "false",
    "contact": "christian.tardif35@gmail.com",
    "date": "02/05/2021",
    "name": "Sur les sentiers de Brocéliande"
  },
  {
    "departement": "56",
    "website": "",
    "_type": "dict",
    "description": "",
    "hour": "Inscriptions de 7h30 à 9h30",
    "city": "COLPO",
    "price": "",
    "organisateur": "GAZELEC CYCLO MORBIHAN",
    "canceled": "false",
    "contact": "gazelec56.cyclo@free.fr",
    "date": "25/04/2021",
    "name": "21ème RANDO DE CORN ER HOET"
  },
  {
    "departement": "44",
    "website": "",
    "_type": "dict",
    "description": "",
    "hour": "7h30 - 10h",
    "city": "Nozay",
    "price": "5€\r\ngratuit pour les moins de 12 ans",
    "organisateur": "NOS Sport Nature",
    "canceled": "false",
    "contact": "contact@nos-sport-nature.fr",
    "date": "25/04/2021",
    "name": "Rando de la Ville Au Chef (8eme édition)"
  },
  {
    "departement": "44",
    "website": "",
    "_type": "dict",
    "description": "",
    "hour": "7h30    9h30",
    "city": "Crossac",
    "price": "marche  4 €    cyclo  3  €\r\nnon licenciés 6 €",
    "organisateur": "Ass cyclo crossac",
    "canceled": "false",
    "contact": "02-40-45-26-68 ou 06-87-26-38-53",
    "date": "25/04/2021",
    "name": "Rando de printemps"
  },
  {
    "departement": "22",
    "website": "",
    "_type": "dict",
    "description": "",
    "hour": "8h30",
    "city": "BELLE ISLE EN TERRE",
    "price": "de 8 à 11€",
    "organisateur": "Association La Pierre Le Bigaut, mucoviscidose",
    "canceled": "false",
    "contact": "contact@plbmuco.org 02 96 45 83 56",
    "date": "25/04/2021",
    "name": "RANDO MUCO"
  },
  {
    "departement": "35",
    "website": "",
    "_type": "dict",
    "description": "",
    "hour": "8H",
    "city": "MEDREAC",
    "price": "",
    "organisateur": "APEL ECOLE ST JOSEPH",
    "canceled": "false",
    "contact": "",
    "date": "18/04/2021",
    "name": "SUR LES SENTIERS DE MEDREAC"
  },
  {
    "departement": "56",
    "website": "",
    "_type": "dict",
    "description": "",
    "hour": "Inscription de 8H00 à 9H30",
    "city": "Monterblanc 56250",
    "price": "VTT : 5.00€\r\nMarche : 4,00€",
    "organisateur": "VELO CLUB MONTERBLANC et CHEMIN FAISANT",
    "canceled": "false",
    "contact": "toinette.le.he@wanadoo.fr",
    "date": "21/11/2021",
    "name": "RANDO STERHUEN"
  },
  {
    "departement": "56",
    "website": "",
    "_type": "dict",
    "description": "",
    "hour": "8h à 9h30",
    "city": "BEIGNON",
    "price": "",
    "organisateur": "AVLS",
    "canceled": "false",
    "contact": "avls56@orange.fr",
    "date": "14/11/2021",
    "name": "10 RANDO DE L'AFF BEIGNON (PORTE SUD DE BROCELIANDE)"
  },
  {
    "departement": "44",
    "website": "",
    "_type": "dict",
    "description": "",
    "hour": "8 heures  9h30",
    "city": "CROSSAC",
    "price": "non licencié 6 €\r\n marche 4€",
    "organisateur": "a c crossac",
    "canceled": "false",
    "contact": "02 40 45 26 68 ou 06 87 26 38 53",
    "date": "14/11/2021",
    "name": "Rando des Colverts"
  },
  {
    "departement": "56",
    "website": "",
    "_type": "dict",
    "description": "",
    "hour": "de 7h30 à 10 h",
    "city": "Pluvigner",
    "price": "5€ VTT\r\n4€ Marche",
    "organisateur": "Club cyclo 'Les Farfadets de Pluvigner'",
    "canceled": "false",
    "contact": "jp.legarrec@orange.fr",
    "date": "07/11/2021",
    "name": "10ème Rando des Lutins"
  },
  {
    "departement": "44",
    "website": "",
    "_type": "dict",
    "description": "",
    "hour": "Départ entre 08h - 10h",
    "city": "NORT SUR ERDRE",
    "price": "5€",
    "organisateur": "NAC Cyclisme et VTT",
    "canceled": "false",
    "contact": "naccyclismevtt@gmail.com",
    "date": "07/11/2021",
    "name": "La Rigolaise"
  },
  {
    "departement": "35",
    "website": "",
    "_type": "dict",
    "description": "",
    "hour": "Départ à partir de 7h30",
    "city": "Laillé",
    "price": "",
    "organisateur": "VC Laillé - Vallons de Vilaine",
    "canceled": "false",
    "contact": "vclaille@gmail.com / 0604436341",
    "date": "31/10/2021",
    "name": "6-ème Rando VTT des Vallons de Vilaine"
  },
  {
    "departement": "29",
    "website": "",
    "_type": "dict",
    "description": "",
    "hour": "Dés 6h30",
    "city": "La Roche Maurice",
    "price": "5",
    "organisateur": "La Roche VTT",
    "canceled": "false",
    "contact": "philippenoel29@orange.fr",
    "date": "10/10/2021",
    "name": "La Roche"
  },
  {
    "departement": "35",
    "website": "",
    "_type": "dict",
    "description": "",
    "hour": "13h30",
    "city": "DOMPIERRE DU CHEMIN",
    "price": "VTT 6€+1€ gobelet\r\nPEDESTRE 5€ +1€ gobelet",
    "organisateur": "Cyclo Club Luitre Dompierre",
    "canceled": "false",
    "contact": "damienzesty@gmail.com",
    "date": "03/10/2021",
    "name": "Les Roches du Saut Roland"
  },
  {
    "departement": "22",
    "website": "",
    "_type": "dict",
    "description": "",
    "hour": "8h30",
    "city": "BELLE ISLE EN TERRE",
    "price": "de 8 à 11€",
    "organisateur": "Association La Pierre Le Bigaut, mucoviscidose",
    "canceled": "false",
    "contact": "contact@plbmuco.org 02 96 45 83 56",
    "date": "03/10/2021",
    "name": "RANDO MUCO"
  },
  {
    "departement": "35",
    "website": "",
    "_type": "dict",
    "description": "",
    "hour": "8H",
    "city": "DOMPIERRE DU CHEMIN",
    "price": "VTT 6€+ 1€ gobelet\r\nPEDESTRE 5€ + 1€ gobelet",
    "organisateur": "Cyclo Club Luitre Dompierre",
    "canceled": "false",
    "contact": "damienzesty@gmail.com",
    "date": "02/10/2021",
    "name": "Les Roches du Saut Roland"
  },
  {
    "departement": "29",
    "website": "",
    "_type": "dict",
    "description": "",
    "hour": "7H30",
    "city": "Lampaul  guimiliau",
    "price": "",
    "organisateur": "Lampaul VTT",
    "canceled": "false",
    "contact": "Lampaulvtt29@gmail.com",
    "date": "19/9/2021",
    "name": "La lampaulaise"
  },
  {
    "departement": "56",
    "website": "",
    "_type": "dict",
    "description": "",
    "hour": "A partir de 8 h00",
    "city": "Peaule",
    "price": "10 euros adultes et 2 euros moins 14 ans",
    "organisateur": "Club (la Benoit Vaugrenard organisation)",
    "canceled": "false",
    "contact": "francoisvaugrenard@orange.fr",
    "date": "18/9/2021",
    "name": "La Benoît Vaugrenard"
  },
  {
    "departement": "22",
    "website": "",
    "_type": "dict",
    "description": "",
    "hour": "7h30 pour inscription",
    "city": "Pluzunet",
    "price": "5 euros",
    "organisateur": "Cyclos pluned",
    "canceled": "false",
    "contact": "Tél. : 06 49 22 45 43",
    "date": "12/9/2021",
    "name": "De vallée en vallée"
  },
  {
    "departement": "22",
    "website": "",
    "_type": "dict",
    "description": "",
    "hour": "12H / 18H",
    "city": "CORSEUL",
    "price": "15 Euros/Coureur",
    "organisateur": "AMC CORSEUL & TEAM VTT BR22",
    "canceled": "false",
    "contact": "br22@outlook.fr / 06.76.58.70.02",
    "date": "04/9/2021",
    "name": "6H VTT La Romaine - Corseul 2021 5ème Edition"
  },
  {
    "departement": "44",
    "website": "",
    "_type": "dict",
    "description": "",
    "hour": "a partir de 8h",
    "city": "clisson",
    "price": "6 €",
    "organisateur": "Vélo Sport Clissonnais",
    "canceled": "false",
    "contact": "pollux.racineux@orange.fr",
    "date": "29/08/2021",
    "name": "la Tivolienne"
  },
  {
    "departement": "35",
    "website": "",
    "_type": "dict",
    "description": "",
    "hour": "7.30",
    "city": "vitré",
    "price": "5 € pour le 35, 50 et 63km\r\n10 € pour le 75 et le 100km",
    "organisateur": "vtt au pays de vitré",
    "canceled": "false",
    "contact": "oliveclemzo@hotmail.fr",
    "date": "29/08/2021",
    "name": "la maxi vtt pays de vitré"
  },
  {
    "departement": "29",
    "website": "",
    "_type": "dict",
    "description": "",
    "hour": "à partir de 7.30",
    "city": "Camaret  / Mer",
    "price": "5 E pour les randos VTT , 16 € pour le raid 100 km VTT (inscription internet indispensable pour le 100 km)",
    "organisateur": "VTT Presqu'île de Crozon",
    "canceled": "false",
    "contact": "menezgorre@gmail.com",
    "date": "29/08/2021",
    "name": "23 ème Rando U et 5 ème VTT Tour de la Presqu'île de Crozon"
  },
  {
    "departement": "29",
    "website": "",
    "_type": "dict",
    "description": "",
    "hour": "7h30",
    "city": "Plouvorn",
    "price": "5€",
    "organisateur": "C C VTT PLOUVORN",
    "canceled": "false",
    "contact": "pierreyvesgouriou@orange.fr",
    "date": "29/07/2021",
    "name": "Tro Lambader"
  },
  {
    "departement": "56",
    "website": "",
    "_type": "dict",
    "description": "",
    "hour": "Départs de 7h30 à 10h00",
    "city": "Pleucadeuc 56140",
    "price": "VTT 5 € - Pédestre 5 € les inscriptions des randos sont remises intégralement à la recherche médicale de la maladie de Charcot à l'Institut du Cerveau",
    "organisateur": "l'ARMC,  l'Aide à la Recherche des Maladies du Cerveau",
    "canceled": "false",
    "contact": "claudehamon@me.com",
    "date": "14/07/2021",
    "name": "10ème Edition de la Jeanne HAMON-FROSTIN"
  },
  {
    "departement": "35",
    "website": "",
    "_type": "dict",
    "description": "",
    "hour": "Inscriptions 7h30 - 9h30",
    "city": "MONTREUIL SOUS PEROUSE",
    "price": "6€",
    "organisateur": "Vélo Loisirs Montreuil",
    "canceled": "false",
    "contact": "nivault.alain@orange.fr",
    "date": "27/06/2021",
    "name": "La Pérouse"
  },
  {
    "departement": "35",
    "website": "",
    "_type": "dict",
    "description": "",
    "hour": "7h30-10h30 suivant les circuits. Clotûre à 13h",
    "city": "Pont-Péan",
    "price": "5€\r\n2,5€ pour les 12-16 ans",
    "organisateur": "Véloxygène Pont-Péan",
    "canceled": "false",
    "contact": "veloxygene35@gmail.com",
    "date": "27/06/2021",
    "name": "21ème Randoxygène"
  },
  {
    "departement": "44",
    "website": "",
    "_type": "dict",
    "description": "",
    "hour": "14 h",
    "city": "Cordemais",
    "price": "15€/pers",
    "organisateur": "vtt Cordemais",
    "canceled": "false",
    "contact": "troisheuresdecolle@gmail.com         Gaylord:06.82.57.84.10",
    "date": "26/06/2021",
    "name": "3 heures de colle"
  },
  {
    "departement": "35",
    "website": "",
    "_type": "dict",
    "description": "",
    "hour": "Inscriptions de 13h à 14h 30",
    "city": "MONTREUIL SOUS PEROUSE",
    "price": "6 €",
    "organisateur": "Vélo Loisirs Montreuil",
    "canceled": "false",
    "contact": "nivault.alain@orange.fr",
    "date": "26/06/2021",
    "name": "La Pérouse"
  },
  {
    "departement": "35",
    "website": "",
    "_type": "dict",
    "description": "",
    "hour": "",
    "city": "LIFFRE",
    "price": "",
    "organisateur": "Club cycliste de Liffré",
    "canceled": "false",
    "contact": "",
    "date": "13/06/2021",
    "name": "La liffréenne"
  },
  {
    "departement": "29",
    "website": "",
    "_type": "dict",
    "description": "",
    "hour": "à partir de 7h30",
    "city": "SIZUN",
    "price": "VTT / VTTAE: 5€\r\nMarche / Trail : 3€",
    "organisateur": "SIZUN VTT AVENTURE",
    "canceled": "false",
    "contact": "jpboucher@laposte.net",
    "date": "06/06/2021",
    "name": "31ème Ronde des Crêtes"
  },
  {
    "departement": "56",
    "website": "",
    "_type": "dict",
    "description": "",
    "hour": "7h30",
    "city": "ST CONGARD",
    "price": "5.00€",
    "organisateur": "AMICALE CYCLISTE CONGARDAISE",
    "canceled": "false",
    "contact": "joelglon@orange.fr /0297435157",
    "date": "23/05/2021",
    "name": "LA CONGARDAISE"
  },
  {
    "departement": "35",
    "website": "",
    "_type": "dict",
    "description": "",
    "hour": "14H",
    "city": "MEDREAC",
    "price": "",
    "organisateur": "APEL ECOLE ST JOSEPH",
    "canceled": "false",
    "contact": "",
    "date": "17/04/2021",
    "name": "SUR LES SENTIERS DE MEDREAC"
  },
  {
    "departement": "35",
    "website": "",
    "_type": "dict",
    "description": "",
    "hour": "20h",
    "city": "SAINT SENOUX",
    "price": "6€ se fera sur inscription limité à 300 VTTs",
    "organisateur": "AVM",
    "canceled": "false",
    "contact": "randosaintsenoux@gmail.com",
    "date": "17/04/2021",
    "name": "Rando Nocturne des Cercliers"
  },
  {
    "departement": "44",
    "website": "",
    "_type": "dict",
    "description": "",
    "hour": "Départ 7h45",
    "city": "ST NICOLAS DE REDON",
    "price": "Cyclo: 3€, Pedestre: 4€, VTT: 5€",
    "organisateur": "VTT St Nicolas de Redon",
    "canceled": "false",
    "contact": "vttsaintnicolasderedon@gmail.com",
    "date": "11/04/2021",
    "name": "Rando VTT - Cyclo et Pedestre avec ravitaillements"
  },
  {
    "departement": "29",
    "website": "",
    "_type": "dict",
    "description": "",
    "hour": "De 07H30 à 10H30",
    "city": "QUERRIEN (29310)",
    "price": "6 euros minimum, gratuit pour les moins de 10 ans",
    "organisateur": "Céline et Stéphane LEUCEMIE ESPOIR 29- Relais Querrien-Mellac-Pays de Quimperlé",
    "canceled": "false",
    "contact": "Tél.FIXE : 02.98.71.34.08 / E-mail : joel.le-goff@wanadoo.fr",
    "date": "11/04/2021",
    "name": "6 éme édition de Leucémie Espoir 'Céline et Stéphane'"
  },
  {
    "departement": "29",
    "website": "",
    "_type": "dict",
    "description": "",
    "hour": "8h30",
    "city": "Saint Thois",
    "price": "",
    "organisateur": "Montagnes Noires vtt",
    "canceled": "false",
    "contact": "",
    "date": "04/04/2021",
    "name": "La Montagnes Noires vtt"
  },
  {
    "departement": "22",
    "website": "",
    "_type": "dict",
    "description": "",
    "hour": "7h 8h engagement départ 9h",
    "city": "Pluzunet",
    "price": "12euros par mail 15 euros sur place",
    "organisateur": "Cyclos pluned",
    "canceled": "false",
    "contact": "QUENAULT.patrick@gmail.com 06 49 22 43 45",
    "date": "04/04/2021",
    "name": "3h vtt relais équipes 2 ou 3 et solo"
  },
  {
    "departement": "56",
    "website": "",
    "_type": "dict",
    "description": "",
    "hour": "à partir de 7H30",
    "city": "BRANDERION",
    "price": "VTT .............  5€\r\nMarche ........  4€",
    "organisateur": "Cyclo Club de Branderion",
    "canceled": "false",
    "contact": "b.fontaine@cyclobranderion.fr ou par tél : 06 66 67 29 92",
    "date": "28/03/2021",
    "name": "11ème Rando du Roch VTT et Marche"
  },
  {
    "departement": "56",
    "website": "",
    "_type": "dict",
    "description": "",
    "hour": "7H30H - 13 H",
    "city": "INZINZAC-LOCHRIST",
    "price": "5 EUROS VTT\r\n4 EUROS PEDESTRE",
    "organisateur": "Club cyclo CLP INZINZAC-LOCHRIST",
    "canceled": "false",
    "contact": "denis.le-reour@wanadoo.fr",
    "date": "21/03/2021",
    "name": "Randonnées VTT et Pédestre de la Forêt de Tremelin"
  },
  {
    "departement": "29",
    "website": "",
    "_type": "dict",
    "description": "",
    "hour": "départs de 8h00 à 10h30",
    "city": "Plounéour Ménez",
    "price": "A venir",
    "organisateur": "A Mi Chemins",
    "canceled": "false",
    "contact": "contact@amichemins.fr",
    "date": "07/03/2021",
    "name": "La printanière 2021"
  },
  {
    "departement": "29",
    "website": "",
    "_type": "dict",
    "description": "",
    "hour": "inscriptions à partir de 8H",
    "city": "Saint Renan",
    "price": "6€ les non licenciés \r\n4€ les marcheurs \r\n2€ les moins de 12 ans",
    "organisateur": "Saint Renan Iroise Vélo",
    "canceled": "false",
    "contact": "bruno.leru29@gmail.com",
    "date": "31/01/2021",
    "name": "An Dro Iroise"
  }
]
